ittools/__init__.py
ittools/core.py
ittools-0.1.3.dist-info/LICENSE
ittools-0.1.3.dist-info/WHEEL
ittools-0.1.3.dist-info/METADATA
ittools-0.1.3.dist-info/RECORD
