Metadata-Version: 2.1
Name: ittools
Version: 0.1.3
Summary: Python Iteration Tools
Home-page: https://github.com/tZ3ma/ittools
License: MIT
Keywords: python-3,iteration,tools,library
Author: Mathias Ammon
Author-email: mathias.ammon@tuhh.de
Requires-Python: >=3.8,<4.0
Classifier: License :: OSI Approved :: MIT License
Classifier: Programming Language :: Python :: 3
Classifier: Programming Language :: Python :: 3.8
Classifier: Programming Language :: Python :: 3.9
Classifier: Programming Language :: Python :: 3.10
Classifier: Programming Language :: Python :: 3.11
Requires-Dist: pandas
Project-URL: Repository, https://github.com/tZ3ma/ittools
